mredu/__init__.py
mredu/simul.py
mredu-1.1.1.dist-info/METADATA
mredu-1.1.1.dist-info/WHEEL
mredu-1.1.1.dist-info/licenses/LICENSE
mredu-1.1.1.dist-info/RECORD
